test_yaac_env/bin/activate_this.py
test_yaac_prod/bin/activate_this.py
yaac/__init__.py
yaac/common/__init__.py
yaac/common/model_loader.py
yaac/common/trainable_model.py
yaac/models/__init__.py
yaac/models/sic/__init__.py
yaac/models/sic/classification_heads.py
yaac/models/sic/sic.py
yaac-0.1.5.dist-info/licenses/LICENSE
yaac-0.1.5.dist-info/METADATA
yaac-0.1.5.dist-info/WHEEL
yaac-0.1.5.dist-info/top_level.txt
yaac-0.1.5.dist-info/RECORD
