Metadata-Version: 2.4
Name: yaac
Version: 0.1.5
Summary: YAAC - Python package for loading and using trained AI models
Author-email: Phil Ammirato <phil.ammirato.yaac@gmail.com>
License-Expression: Apache-2.0
Project-URL: Homepage, https://github.com/withyaac/yaac
Project-URL: Repository, https://github.com/withyaac/yaac
Project-URL: Documentation, https://github.com/withyaac/yaac#readme
Project-URL: Bug Tracker, https://github.com/withyaac/yaac/issues
Keywords: machine-learning,deep-learning,pytorch,image-classification,computer-vision
Classifier: Development Status :: 3 - Alpha
Classifier: Intended Audience :: Developers
Classifier: Intended Audience :: Science/Research
Classifier: Operating System :: OS Independent
Classifier: Programming Language :: Python :: 3
Classifier: Programming Language :: Python :: 3.10
Classifier: Programming Language :: Python :: 3.11
Classifier: Programming Language :: Python :: 3.12
Classifier: Topic :: Scientific/Engineering :: Artificial Intelligence
Classifier: Topic :: Software Development :: Libraries :: Python Modules
Requires-Python: >=3.10
License-File: LICENSE
Requires-Dist: numpy<3.0.0,>=2.0.0
Requires-Dist: safetensors>=0.5.0
Requires-Dist: torch<3.0.0,>=2.0.0
Requires-Dist: torchvision<0.24.0,>=0.15.0
Requires-Dist: transformers>=4.40.0
Provides-Extra: dev
Requires-Dist: mypy>=1.8.0; extra == "dev"
Requires-Dist: ruff>=0.3.0; extra == "dev"
Requires-Dist: pytest>=8.0.0; extra == "dev"
Dynamic: license-file
